EasyLM/__init__.py
EasyLM/base_model.py
EasyLM/data_preprocessor.py
EasyLM/exceptions.py
EasyLM/linear_model.py
EasyLM/model_comparator.py
EasyLM/plot_helper.py
EasyLM/plot_utils.py
EasyLM/regression_stats.py
EasyLM/summary_formatter.py
EasyLM/summary_main.py
EasyLM/utils.py
amoang_easylm-0.1.6.dist-info/licenses/LICENSE
amoang_easylm-0.1.6.dist-info/METADATA
amoang_easylm-0.1.6.dist-info/WHEEL
amoang_easylm-0.1.6.dist-info/top_level.txt
amoang_easylm-0.1.6.dist-info/RECORD
