Metadata-Version: 2.4
Name: amoang-easylm
Version: 0.1.6
Summary: R-style linear regression in Python with comprehensive statistics and visualizations
Author-email: Kyle Paolo G Bautro <kyleforthedamaged@example.com>, Carl Dane Penano <carl.penano@example.com>, Joshua Oraiz <oraiz.joshuadavid@example.com>, Symond Ridge Fernandez <symond.fernandez@example.com>, Yochanan Bangoy <mahojowk@gmail.com>
License: MIT
Project-URL: Homepage, https://github.com/apaolol/EasyLM
Project-URL: Documentation, https://github.com/apaolol/EasyLM#readme
Project-URL: Repository, https://github.com/apaolol/EasyLM
Project-URL: Issues, https://github.com/apaolol/EasyLM/issues
Keywords: linear-regression,statistics,r-style,ols,regression-analysis
Classifier: Development Status :: 4 - Beta
Classifier: Intended Audience :: Science/Research
Classifier: Intended Audience :: Developers
Classifier: License :: OSI Approved :: MIT License
Classifier: Programming Language :: Python :: 3
Classifier: Programming Language :: Python :: 3.7
Classifier: Programming Language :: Python :: 3.8
Classifier: Programming Language :: Python :: 3.9
Classifier: Programming Language :: Python :: 3.10
Classifier: Programming Language :: Python :: 3.11
Classifier: Topic :: Scientific/Engineering :: Mathematics
Classifier: Topic :: Software Development :: Libraries :: Python Modules
Requires-Python: >=3.7
License-File: LICENSE
Requires-Dist: numpy>=1.20.0
Requires-Dist: pandas>=1.3.0
Requires-Dist: scipy>=1.7.0
Requires-Dist: matplotlib>=3.4.0
Requires-Dist: seaborn>=0.11.0
Provides-Extra: dev
Requires-Dist: pytest>=6.0.0; extra == "dev"
Requires-Dist: pytest-cov>=2.12.0; extra == "dev"
Requires-Dist: black>=21.0; extra == "dev"
Requires-Dist: flake8>=3.9.0; extra == "dev"
Dynamic: license-file
